coopui/IAtomicUserInteraction.py
coopui/__init__.py
coopui/parameterRequestFactory.py
coopui/cli/CliAtomicUserInteraction.py
coopui/cli/CliMenu.py
coopui/cli/__init__.py
coopui/cli/fileContentReturn.py
coopui/cli/typeToRequestMapping.py
coopui-0.21.dist-info/LICENSE
coopui-0.21.dist-info/METADATA
coopui-0.21.dist-info/WHEEL
coopui-0.21.dist-info/top_level.txt
coopui-0.21.dist-info/RECORD
