Metadata-Version: 2.1
Name: coopui
Version: 0.21
Summary: Package dedicated for holding tooling that allows a developer to interact with a user
Home-page: https://github.com/tylertjburns/coopui
Author: tburns
Author-email: tyler.tj.burns@gmail.com
License: MIT
Platform: UNKNOWN
Classifier: Development Status :: 3 - Alpha
Classifier: License :: OSI Approved :: MIT License
Classifier: Programming Language :: Python
Classifier: Programming Language :: Python :: 3.5
Classifier: Programming Language :: Python :: 3.6
Classifier: Topic :: Software Development :: Libraries
Classifier: Topic :: Software Development :: Libraries :: Python Modules
Classifier: Intended Audience :: Developers
Requires-Python: >3.5
License-File: LICENSE
Requires-Dist: cooptools (==1.18)
Requires-Dist: numpy (==1.19.4)
Requires-Dist: pandas (==1.1.5)
Requires-Dist: python-dateutil (==2.8.1)
Requires-Dist: pytz (==2020.4)
Requires-Dist: six (==1.15.0)
